swmcloudgate/__init__.py
swmcloudgate/cache.py
swmcloudgate/config.py
swmcloudgate/logging.yaml
swmcloudgate/main.py
swmcloudgate/start.py
swmcloudgate/update-azure-caches.py
swmcloudgate/routers/__init__.py
swmcloudgate/routers/baseconnector.py
swmcloudgate/routers/models.py
swmcloudgate/routers/azure/__init__.py
swmcloudgate/routers/azure/connector.py
swmcloudgate/routers/azure/converters.py
swmcloudgate/routers/azure/images.py
swmcloudgate/routers/azure/partitions.py
swmcloudgate/routers/azure/sizes.py
swmcloudgate/routers/azure/templates/cloud-init.sh
swmcloudgate/routers/azure/templates/cloud-init.yaml
swmcloudgate/routers/azure/templates/partition.json
swmcloudgate/routers/openstack/__init__.py
swmcloudgate/routers/openstack/connector.py
swmcloudgate/routers/openstack/converters.py
swmcloudgate/routers/openstack/images.py
swmcloudgate/routers/openstack/partitions.py
swmcloudgate/routers/openstack/sizes.py
swmcloudgate/routers/openstack/templates/cloud-init.sh
swmcloudgate/routers/openstack/templates/heat_stack.yaml
swmcloudgate-0.1.8.dist-info/LICENSE
swmcloudgate-0.1.8.dist-info/METADATA
swmcloudgate-0.1.8.dist-info/WHEEL
swmcloudgate-0.1.8.dist-info/top_level.txt
swmcloudgate-0.1.8.dist-info/RECORD
